{
  "file": "line.png",
  "frames": {
    "line1": {
      "x": 0,
      "y": 1610,
      "w": 688,
      "h": 16,
      "offX": 1,
      "offY": 0,
      "sourceW": 690,
      "sourceH": 16
    },
    "line2": {
      "x": 0,
      "y": 0,
      "w": 694,
      "h": 296,
      "offX": 0,
      "offY": 0,
      "sourceW": 694,
      "sourceH": 296
    },
    "line3": {
      "x": 0,
      "y": 1033,
      "w": 690,
      "h": 152,
      "offX": 0,
      "offY": 0,
      "sourceW": 690,
      "sourceH": 152
    },
    "line4": {
      "x": 0,
      "y": 878,
      "w": 687,
      "h": 154,
      "offX": 1,
      "offY": 0,
      "sourceW": 689,
      "sourceH": 154
    },
    "line5": {
      "x": 695,
      "y": 287,
      "w": 677,
      "h": 275,
      "offX": 0,
      "offY": 0,
      "sourceW": 677,
      "sourceH": 275
    },
    "line6": {
      "x": 692,
      "y": 838,
      "w": 690,
      "h": 156,
      "offX": 0,
      "offY": 0,
      "sourceW": 690,
      "sourceH": 156
    },
    "line7": {
      "x": 692,
      "y": 563,
      "w": 676,
      "h": 274,
      "offX": 0,
      "offY": 0,
      "sourceW": 676,
      "sourceH": 274
    },
    "lined1": {
      "x": 0,
      "y": 1627,
      "w": 676,
      "h": 2,
      "offX": 0,
      "offY": 0,
      "sourceW": 676,
      "sourceH": 2
    },
    "lined2": {
      "x": 0,
      "y": 297,
      "w": 690,
      "h": 290,
      "offX": 0,
      "offY": 0,
      "sourceW": 690,
      "sourceH": 290
    },
    "lined3": {
      "x": 0,
      "y": 1471,
      "w": 676,
      "h": 138,
      "offX": 0,
      "offY": 0,
      "sourceW": 676,
      "sourceH": 138
    },
    "lined4": {
      "x": 0,
      "y": 1329,
      "w": 675,
      "h": 141,
      "offX": 0,
      "offY": 0,
      "sourceW": 675,
      "sourceH": 141
    },
    "lined5": {
      "x": 0,
      "y": 588,
      "w": 691,
      "h": 289,
      "offX": 0,
      "offY": 0,
      "sourceW": 691,
      "sourceH": 289
    },
    "lined6": {
      "x": 0,
      "y": 1186,
      "w": 676,
      "h": 142,
      "offX": 0,
      "offY": 0,
      "sourceW": 676,
      "sourceH": 142
    },
    "lined7": {
      "x": 695,
      "y": 0,
      "w": 688,
      "h": 286,
      "offX": 1,
      "offY": 1,
      "sourceW": 690,
      "sourceH": 287
    }
  }
}