{"width":510,"SubTexture":[{"width":189,"y":604,"height":100,"name":"yezi6_3","x":186},{"width":183,"y":539,"height":125,"name":"yezi6_2","x":1},{"width":237,"y":255,"height":184,"name":"yezi6_1","x":252},{"width":157,"y":441,"height":161,"name":"yezi6_0","x":252},{"width":74,"y":666,"height":50,"name":"yezi5_5","x":85},{"frameWidth":65,"y":539,"frameHeight":57,"width":63,"frameX":-1,"height":55,"name":"yezi5_4","frameY":-1,"x":186},{"frameWidth":81,"y":706,"frameHeight":28,"width":79,"frameX":-1,"height":26,"name":"yezi5_3","frameY":-1,"x":161},{"frameWidth":35,"y":778,"frameHeight":77,"width":33,"frameX":-1,"height":75,"name":"yezi5_2","frameY":-1,"x":1},{"frameWidth":91,"y":216,"frameHeight":29,"width":89,"frameX":-1,"height":27,"name":"yezi5_1","frameY":-1,"x":294},{"frameWidth":76,"y":557,"frameHeight":42,"width":74,"frameX":-1,"height":40,"name":"yezi5_0","frameY":-1,"x":411},{"frameWidth":24,"y":666,"frameHeight":26,"width":22,"frameX":-1,"height":24,"name":"yezi4_3","frameY":-1,"x":161},{"frameWidth":99,"y":441,"frameHeight":116,"width":97,"frameX":-1,"height":114,"name":"yezi4_2","frameY":-1,"x":411},{"frameWidth":51,"y":666,"frameHeight":112,"width":49,"frameX":-1,"height":110,"name":"yezi4_1","frameY":-1,"x":1},{"frameWidth":123,"y":604,"frameHeight":122,"width":121,"frameX":-1,"height":120,"name":"yezi4_0","frameY":-1,"x":377},{"frameWidth":24,"y":718,"frameHeight":50,"width":22,"frameX":-1,"height":48,"name":"yezi3_4","frameY":-1,"x":85},{"frameWidth":33,"y":666,"frameHeight":147,"width":31,"frameX":-1,"height":145,"name":"yezi3_3","frameY":-1,"x":52},{"frameWidth":66,"y":1,"frameHeight":109,"width":64,"frameX":-1,"height":107,"name":"yezi3_2","frameY":-1,"x":440},{"frameWidth":52,"y":110,"frameHeight":119,"width":50,"frameX":-1,"height":117,"name":"yezi3_1","frameY":-1,"x":440},{"width":249,"y":255,"height":282,"name":"yezi2_0","x":1},{"width":144,"y":1,"height":213,"name":"yezi1_1","x":294},{"width":291,"y":1,"height":252,"name":"yezi1_0","x":1}],"height":855,"name":"shuye_1","imagePath":"shuye_1_tex.png"}